[
  {
    "question": "ఇది ఎవరి పరమగీతము?",
    "opt1": "సొలొమోనుది",
    "opt2": "దావీదుది",
    "opt3": "మోషేది",
    "opt4": "సమూయేలుది",
    "correct": "సొలొమోనుది",
    "explanation": "పరమగీతము 1:1 - సొలొమోనుది అని చెప్పబడిన పరమగీతము.",
    "book": "SongofSolomon",
    "category": "OldTestament",
    "chapter": 1
  },
  {
    "question": "నీ ప్రేమ దేనికంటె మధురము?",
    "opt1": "తేనె కంటె",
    "opt2": "పాలు కంటె",
    "opt3": "ద్రాక్షారసముకన్న",
    "opt4": "పండ్ల కంటె",
    "correct": "ద్రాక్షారసముకన్న",
    "explanation": "పరమగీతము 1:2 - నీ ప్రేమ ద్రాక్షారసముకన్న మధురము.",
    "book": "SongofSolomon",
    "category": "OldTestament",
    "chapter": 1
  },
  {
    "question": "యెరూషలేము కుమార్తెలారా, నేను నల్లనిదాననైనను ఎట్టిదానను?",
    "opt1": "వికారమైనదానను",
    "opt2": "సౌందర్యవతిని",
    "opt3": "పొట్టిదానను",
    "opt4": "బలహీనురాలిని",
    "correct": "సౌందర్యవతిని",
    "explanation": "పరమగీతము 1:5 - యెరూషలేము కుమార్తెలారా, నేను నల్లనిదాననైనను సౌందర్యవతిని.",
    "book": "SongofSolomon",
    "category": "OldTestament",
    "chapter": 1
  },
  {
    "question": "ఆమె నల్లగా ఉండుటకు గల కారణమేమి?",
    "opt1": "ఆమెకు ఆనారోగ్యము",
    "opt2": "ఆమె పుట్టుకతోనే నల్లనిది",
    "opt3": "ఆమె రంగు వేసుకొనెను",
    "opt4": "ఎండ తగిలినందున (సూర్యుని దృష్టి నా మీద పడినందున)",
    "correct": "ఎండ తగిలినందున (సూర్యుని దృష్టి నా మీద పడినందున)",
    "explanation": "పరమగీతము 1:6 - నన్ను తేరి చూడకుడి, ఎండ తగిలినందున నేను నలుపెక్కితిని.",
    "book": "SongofSolomon",
    "category": "OldTestament",
    "chapter": 1
  },
  {
    "question": "ఆమె మీద ఎవరు కోపించిరి?",
    "opt1": "తన తల్లి కుమారులు",
    "opt2": "రాజు",
    "opt3": "చెలికత్తెలు",
    "opt4": "శత్రువులు",
    "correct": "తన తల్లి కుమారులు",
    "explanation": "పరమగీతము 1:6 - నా తల్లి కుమారులు నా మీద కోపించి నన్ను ద్రాక్షతోటలకు కావలికత్తెగా ఉంచిరి.",
    "book": "SongofSolomon",
    "category": "OldTestament",
    "chapter": 1
  },
  {
    "question": "ఆమె తనను తాను ఎక్కడ మేపుకొనువానిగా వర్ణించుకొనెను?",
    "opt1": "అరణ్యములో",
    "opt2": "సముద్ర తీరమున",
    "opt3": "మధ్యాహ్నకాలమందు మందను పరుండబెట్టువానిగా",
    "opt4": "రాజనగరులో",
    "correct": "మధ్యాహ్నకాలమందు మందను పరుండబెట్టువానిగా",
    "explanation": "పరమగీతము 1:7 - నా ప్రాణ ప్రియుడా, నీ మందను నీవెక్కడ మేపుదువో, మధ్యాహ్నకాలమందు ఎక్కడ పరుండబెట్టుదువో నాతో చెప్పుము.",
    "book": "SongofSolomon",
    "category": "OldTestament",
    "chapter": 1
  },
  {
    "question": "ప్రియుడు ఆమెను దేనితో పోల్చెను?",
    "opt1": "ఒంటెతో",
    "opt2": "ఫరో రథములకు కట్టిన గుఱ్ఱముతో",
    "opt3": "లేడితో",
    "opt4": "పావురముతో",
    "correct": "ఫరో రథములకు కట్టిన గుఱ్ఱముతో",
    "explanation": "పరమగీతము 1:9 - నా ప్రియురాలా, ఫరో రథములకు కట్టిన గుఱ్ఱముతో నిన్ను పోల్చుదును.",
    "book": "SongofSolomon",
    "category": "OldTestament",
    "chapter": 1
  },
  {
    "question": "రాజు విందులో కూర్చుని యుండగా దేని సువాసన వ్యాపించెను?",
    "opt1": "గులాబీ పూల",
    "opt2": "ధూపము",
    "opt3": "ఆహారము",
    "opt4": "నటామాంసి (Spikenard)",
    "correct": "నటామాంసి (Spikenard)",
    "explanation": "పరమగీతము 1:12 - రాజు విందులో కూర్చుని యుండగా నా నటామాంసి సువాసన వ్యాపించెను.",
    "book": "SongofSolomon",
    "category": "OldTestament",
    "chapter": 1
  },
  {
    "question": "నా ప్రియుడు నాకు ఎటువంటివాడు?",
    "opt1": "నా రొమ్మున నుండు గోపరసపు కట్ట (Bundle of myrrh)",
    "opt2": "బంగారు ఆభరణము",
    "opt3": "వజ్రము",
    "opt4": "కిరీటము",
    "correct": "నా రొమ్మున నుండు గోపరసపు కట్ట (Bundle of myrrh)",
    "explanation": "పరమగీతము 1:13 - నా ప్రియుడు నాకు నా రొమ్మున నుండు గోపరసపు కట్ట.",
    "book": "SongofSolomon",
    "category": "OldTestament",
    "chapter": 1
  },
  {
    "question": "మన ఇల్లు ఎట్టిది?",
    "opt1": "రాతి ఇల్లు",
    "opt2": "బంగారు ఇల్లు",
    "opt3": "దూలములు దేవదారు మ్రానులు, సరంబీలు సరళపు మ్రానులు",
    "opt4": "గుడారము",
    "correct": "దూలములు దేవదారు మ్రానులు, సరంబీలు సరళపు మ్రానులు",
    "explanation": "పరమగీతము 1:17 - మన ఇంటి దూలములు దేవదారు మ్రానులు, మన సరంబీలు సరళపు మ్రానులు.",
    "book": "SongofSolomon",
    "category": "OldTestament",
    "chapter": 1
  },
  {
    "question": "ఆమె తనను తాను ఏమని వర్ణించుకొనెను?",
    "opt1": "షారోను పొలములో పూయు పువ్వును, లోయలలో పుట్టుట తామరను",
    "opt2": "తోటలో పూయు గులాబీని",
    "opt3": "అడవిలో పూయు మల్లెను",
    "opt4": "కొండ మీద ఉండు వృక్షమును",
    "correct": "షారోను పొలములో పూయు పువ్వును, లోయలలో పుట్టుట తామరను",
    "explanation": "పరమగీతము 2:1 - నేను షారోను పొలములో పూయు పువ్వును, లోయలలో పుట్టుట తామరను.",
    "book": "SongofSolomon",
    "category": "OldTestament",
    "chapter": 2
  },
  {
    "question": "ముండ్లతుప్పలలో తామరపువ్వు ఎట్లుండునో కుమార్తెలలో నా ప్రియురాలు...",
    "opt1": "వాడిపోయినట్లున్నది",
    "opt2": "కనబడకుండా ఉన్నది",
    "opt3": "అట్లున్నది",
    "opt4": "నలుపుగా ఉన్నది",
    "correct": "అట్లున్నది",
    "explanation": "పరమగీతము 2:2 - ముండ్లతుప్పలలో తామరపువ్వు ఎట్లుండునో కుమార్తెలలో నా ప్రియురాలు అట్లున్నది.",
    "book": "SongofSolomon",
    "category": "OldTestament",
    "chapter": 2
  },
  {
    "question": "అడవి చెట్లలో జల్దరు వృక్షము ఎట్లుండునో కుమారులలో నా ప్రియుడు అట్లున్నాడు. ఆమె అతని నీడన కూర్చుండుటకు...",
    "opt1": "భయపడెను",
    "opt2": "వాంఛించెను (మిక్కిలి ఆశపడెను)",
    "opt3": "ఇష్టపడలేదు",
    "opt4": "అలసిపోయెను",
    "correct": "వాంఛించెను (మిక్కిలి ఆశపడెను)",
    "explanation": "పరమగీతము 2:3 - అతని నీడన కూర్చుండవలెనని నేను మిక్కిలి ఆశపడితిని.",
    "book": "SongofSolomon",
    "category": "OldTestament",
    "chapter": 2
  },
  {
    "question": "నా మీద ఆడుచున్న ధ్వజము ఏది?",
    "opt1": "సమాధానము",
    "opt2": "సంతోషము",
    "opt3": "విజయము",
    "opt4": "ప్రేమ",
    "correct": "ప్రేమ",
    "explanation": "పరమగీతము 2:4 - అతడు విందు ఇంటికి నన్ను తోడుకొని పోయెను, నా మీద ప్రేమయ అను ధ్వజము ఎత్తెను.",
    "book": "SongofSolomon",
    "category": "OldTestament",
    "chapter": 2
  },
  {
    "question": "ఆమెకు ప్రేమాయాసము కలిగెను గనుక వేటితో ఆమెను బలపరచమని కోరెను?",
    "opt1": "ద్రాక్షపండ్ల అడలతోను, జల్దరు పండ్లతోను",
    "opt2": "రొట్టెలతోను",
    "opt3": "నీళ్లతోను",
    "opt4": "మాంసముతోను",
    "correct": "ద్రాక్షపండ్ల అడలతోను, జల్దరు పండ్లతోను",
    "explanation": "పరమగీతము 2:5 - ద్రాక్షపండ్ల అడల చేత నన్ను బలపరచుడి, జల్దరు పండ్ల చేత నన్ను సేదదీర్చుడి; నాకు ప్రేమాయాసము కలిగెను.",
    "book": "SongofSolomon",
    "category": "OldTestament",
    "chapter": 2
  },
  {
    "question": "తనకు ఇష్టమగు వరకు ప్రేమను లేపవద్దనియు కలతపరచవద్దనియు ఆమె ఎవరితో ప్రమాణము చేయించెను?",
    "opt1": "సైనికులతో",
    "opt2": "ప్రియునితో",
    "opt3": "యెరూషలేము కుమార్తెలతో",
    "opt4": "తల్లితో",
    "correct": "యెరూషలేము కుమార్తెలతో",
    "explanation": "పరమగీతము 2:7 - యెరూషలేము కుమార్తెలారా... మీకు ఆన కలుగజేయుచున్నాను; ప్రేమకు ఇష్టమగు వరకు మీరు దాని లేపకుడు, కలతపరచకుడి.",
    "book": "SongofSolomon",
    "category": "OldTestament",
    "chapter": 2
  },
  {
    "question": "ఆమె ప్రియుడు వేటి మీద గంతులు వేయుచు వచ్చెను?",
    "opt1": "పర్వతముల మీద",
    "opt2": "సముద్రము మీద",
    "opt3": "భవనముల మీద",
    "opt4": "మేఘముల మీద",
    "correct": "పర్వతముల మీద",
    "explanation": "పరమగీతము 2:8 - ఆలకించుము, నా ప్రియుని స్వరము వినబడుచున్నది; ఇదిగో అతడు పర్వతముల మీద గంతులు వేయుచు... వచ్చుచున్నాడు.",
    "book": "SongofSolomon",
    "category": "OldTestament",
    "chapter": 2
  },
  {
    "question": "ఆమె ప్రియుడు దేనిని పోలియున్నాడు?",
    "opt1": "సింహమును",
    "opt2": "గింకను (Gazelle), లేడి పిల్ల (Young Hart) ను",
    "opt3": "డేగను",
    "opt4": "పావురమును",
    "correct": "గింకను (Gazelle), లేడి పిల్ల (Young Hart) ను",
    "explanation": "పరమగీతము 2:9 - నా ప్రియుడు గింకను పోలియున్నాడు, లేడి పిల్లను పోలియున్నాడు.",
    "book": "SongofSolomon",
    "category": "OldTestament",
    "chapter": 2
  },
  {
    "question": "ఏ కాలము గతించెనని ప్రియుడు చెప్పెను?",
    "opt1": "చలికాలము",
    "opt2": "ఎండాకాలము",
    "opt3": "వసంతకాలము",
    "opt4": "కోతకాలము",
    "correct": "చలికాలము",
    "explanation": "పరమగీతము 2:11 - చలికాలము గడిచిపోయెను, వర్షకాలము తీరిపోయెను.",
    "book": "SongofSolomon",
    "category": "OldTestament",
    "chapter": 2
  },
  {
    "question": "దేశమందంతట దేని స్వరము వినబడుచున్నది?",
    "opt1": "సింహపు గర్జన",
    "opt2": "పావురపు స్వరము",
    "opt3": "యుద్ధ ధ్వని",
    "opt4": "ఉరుము",
    "correct": "పావురపు స్వరము",
    "explanation": "పరమగీతము 2:12 - దేశమందంతట పావురపు స్వరము వినబడుచున్నది.",
    "book": "SongofSolomon",
    "category": "OldTestament",
    "chapter": 2
  },
  {
    "question": "ద్రాక్షావలులను పాడుచేయు వేటిని పట్టుకొనుమని చెప్పెను?",
    "opt1": "పక్షులను",
    "opt2": "పాములను",
    "opt3": "గుంట నక్కలను (Little foxes)",
    "opt4": "ఎలుకలను",
    "correct": "గుంట నక్కలను (Little foxes)",
    "explanation": "పరమగీతము 2:15 - ద్రాక్షావలులను పాడుచేయు నక్కలను గుంట నక్కలను మన కొరకు పట్టుకొనుడి.",
    "book": "SongofSolomon",
    "category": "OldTestament",
    "chapter": 2
  },
  {
    "question": "నా ప్రియుడు నావాడు, నేను అతనిదానను; అతడు ఎక్కడ మందను మేపుచున్నాడు?",
    "opt1": "అరణ్యములో",
    "opt2": "కొండ మీద",
    "opt3": "నది ఒడ్డున",
    "opt4": "తామర పూల మధ్యను (Among the lilies)",
    "correct": "తామర పూల మధ్యను (Among the lilies)",
    "explanation": "పరమగీతము 2:16 - అతడు తామర పూల మధ్యను మందను మేపుచున్నాడు.",
    "book": "SongofSolomon",
    "category": "OldTestament",
    "chapter": 2
  },
  {
    "question": "ఆమె రాత్రివేళ పడక మీద ఎవరిని వెదకెను?",
    "opt1": "తన తల్లిని",
    "opt2": "కాపరులను",
    "opt3": "తన ప్రాణ ప్రియుని",
    "opt4": "స్నేహితురాలిని",
    "correct": "తన ప్రాణ ప్రియుని",
    "explanation": "పరమగీతము 3:1 - రాత్రివేళ పడక మీద నా ప్రాణ ప్రియుని నేను వెదకితిని.",
    "book": "SongofSolomon",
    "category": "OldTestament",
    "chapter": 3
  },
  {
    "question": "ఆమె తన ప్రియుని వెదకుటకు ఎక్కడికి వెళ్ళెను?",
    "opt1": "అరణ్యమునకు",
    "opt2": "పట్టణములోనికి, వీధులలోనికీ, రాజమార్గములలోనికీ",
    "opt3": "రాజనగరుకు",
    "opt4": "తోటలోనికి",
    "correct": "పట్టణములోనికి, వీధులలోనికీ, రాజమార్గములలోనికీ",
    "explanation": "పరమగీతము 3:2 - నేను లేచి పట్టణములోనికి వెళ్ళెదను; వీధులలోను రాజమార్గములలోను తిరిగి నా ప్రాణ ప్రియుని వెదకుదును.",
    "book": "SongofSolomon",
    "category": "OldTestament",
    "chapter": 3
  },
  {
    "question": "ఆమెకు ఎవరు ఎదురుపడిరి?",
    "opt1": "సైనికులు",
    "opt2": "దొంగలు",
    "opt3": "పట్టణములో తిరుగు కాపరులు (Watchmen)",
    "opt4": "వర్తకులు",
    "correct": "పట్టణములో తిరుగు కాపరులు (Watchmen)",
    "explanation": "పరమగీతము 3:3 - పట్టణములో తిరుగు కాపరులు నాకు ఎదురుపడిరి.",
    "book": "SongofSolomon",
    "category": "OldTestament",
    "chapter": 3
  },
  {
    "question": "ఆమె తన ప్రియుని కనుగొని ఎక్కడికి తీసుకొని వచ్చెను?",
    "opt1": "రాజనగరుకు",
    "opt2": "ద్రాక్షతోటకు",
    "opt3": "తన స్నేహితురాలి ఇంటికి",
    "opt4": "తన తల్లి ఇంటికిని, తనను కనినదాని గదిలోనికిని",
    "correct": "తన తల్లి ఇంటికిని, తనను కనినదాని గదిలోనికిని",
    "explanation": "పరమగీతము 3:4 - అతని పట్టుకొని నా తల్లి ఇంటికిని నన్ను కనినదాని గదిలోనికిని తోడుకొని వచ్చు వరకు నేను అతనిని పోనియ్యనైతిని.",
    "book": "SongofSolomon",
    "category": "OldTestament",
    "chapter": 3
  },
  {
    "question": "అరణ్యమార్గమున వచ్చునది ఏది?",
    "opt1": "పొగస్తంభము వంటిది (సొలొమోను పల్లకి)",
    "opt2": "మేఘము",
    "opt3": "రథము",
    "opt4": "సైన్యము",
    "correct": "పొగస్తంభము వంటిది (సొలొమోను పల్లకి)",
    "explanation": "పరమగీతము 3:6 - బోళముతోను సాంబ్రాణితోను... పరిమళించి పొగస్తంభములవలే అరణ్యమార్గమున వచ్చునది ఏది?",
    "book": "SongofSolomon",
    "category": "OldTestament",
    "chapter": 3
  },
  {
    "question": "సొలొమోను పల్లకి చుట్టూ ఎంతమంది శూరులు ఉన్నారు?",
    "opt1": "నలభై మంది",
    "opt2": "అరవై మంది",
    "opt3": "వంద మంది",
    "opt4": "ముప్పది మంది",
    "correct": "అరవై మంది",
    "explanation": "పరమగీతము 3:7 - సొలొమోను పల్లకి చుట్టూ ఇశ్రాయేలీయుల శూరులలో అరవై మంది శూరులున్నారు.",
    "book": "SongofSolomon",
    "category": "OldTestament",
    "chapter": 3
  },
  {
    "question": "వారందరూ ఏమి ధరించుకొని యున్నారు?",
    "opt1": "కత్తులు (ఖడ్గధారులు)",
    "opt2": "ఈటెలు",
    "opt3": "డాలులు",
    "opt4": "విల్లులు",
    "correct": "కత్తులు (ఖడ్గధారులు)",
    "explanation": "పరమగీతము 3:8 - వారందరూ ఖడ్గధారులు, యుద్ధవీరులు.",
    "book": "SongofSolomon",
    "category": "OldTestament",
    "chapter": 3
  },
  {
    "question": "రాత్రి భయమును బట్టి ప్రతివాడు తన నడుమున ఏమి కట్టుకొనియున్నాడు?",
    "opt1": "దట్టి",
    "opt2": "ఖడ్గము",
    "opt3": "వస్త్రము",
    "opt4": "సంచి",
    "correct": "ఖడ్గము",
    "explanation": "పరమగీతము 3:8 - రాత్రి భయమును బట్టి ప్రతివాడు తన నడుమున ఖడ్గము కట్టుకొనియున్నాడు.",
    "book": "SongofSolomon",
    "category": "OldTestament",
    "chapter": 3
  },
  {
    "question": "సొలొమోను తన కొరకు పల్లకిని ఏ మ్రానుతో చేయించుకొనెను?",
    "opt1": "తుమ్మ కర్రతో",
    "opt2": "గంధపు చెక్కతో",
    "opt3": "లెబానోను మ్రానుతో",
    "opt4": "ఒలీవ కర్రతో",
    "correct": "లెబానోను మ్రానుతో",
    "explanation": "పరమగీతము 3:9 - రాజైన సొలొమోను లెబానోను మ్రానుతో తనకొక పల్లకిని చేయించుకొనెను.",
    "book": "SongofSolomon",
    "category": "OldTestament",
    "chapter": 3
  },
  {
    "question": "దాని స్తంభములు దేనితో చేయబడెను?",
    "opt1": "బంగారముతో",
    "opt2": "వెండితో",
    "opt3": "ఇత్తడితో",
    "opt4": "ఇనుముతో",
    "correct": "వెండితో",
    "explanation": "పరమగీతము 3:10 - దాని స్తంభములు వెండివి.",
    "book": "SongofSolomon",
    "category": "OldTestament",
    "chapter": 3
  },
  {
    "question": "దాని పీఠము దేనితో చేయబడెను?",
    "opt1": "వెండితో",
    "opt2": "రాతితో",
    "opt3": "బంగారముతో",
    "opt4": "చెక్కతో",
    "correct": "బంగారముతో",
    "explanation": "పరమగీతము 3:10 - దాని పీఠము బంగారుది.",
    "book": "SongofSolomon",
    "category": "OldTestament",
    "chapter": 3
  },
  {
    "question": "సొలొమోనుకు కిరీటమును ఎవరు పెట్టిరి?",
    "opt1": "యాజకుడు",
    "opt2": "అతని తల్లి",
    "opt3": "ప్రవక్త",
    "opt4": "దావీదు",
    "correct": "అతని తల్లి",
    "explanation": "పరమగీతము 3:11 - వివాహదినమందు... అతని తల్లి అతనికి పెట్టిన కిరీటముతో రాజైన సొలొమోనును చూడుడి.",
    "book": "SongofSolomon",
    "category": "OldTestament",
    "chapter": 3
  },
  {
    "question": "ప్రియుడు ఆమె కనులను దేనితో పోల్చెను?",
    "opt1": "పావురములతో",
    "opt2": "నక్షత్రములతో",
    "opt3": "దీపములతో",
    "opt4": "అగ్నితో",
    "correct": "పావురములతో",
    "explanation": "పరమగీతము 4:1 - నీ ముసుగుగుండా నీ కన్నులు పావురముల్లా ఉన్నాయి.",
    "book": "SongofSolomon",
    "category": "OldTestament",
    "chapter": 4
  },
  {
    "question": "ఆమె తలవెండ్రుకలు దేనిని పోలియున్నవి?",
    "opt1": "మబ్బులను",
    "opt2": "బంగారు తీగలను",
    "opt3": "గిలాదు పర్వతము మీద పండుకొను మేకల మందను",
    "opt4": "నల్లని ద్రాక్షలను",
    "correct": "గిలాదు పర్వతము మీద పండుకొను మేకల మందను",
    "explanation": "పరమగీతము 4:1 - నీ తలవెండ్రుకలు గిలాదు పర్వతము మీద పండుకొను మేకల మందను పోలియున్నవి.",
    "book": "SongofSolomon",
    "category": "OldTestament",
    "chapter": 4
  },
  {
    "question": "ఆమె పళ్లు ఎట్లున్నవి?",
    "opt1": "ముత్యముల వలె",
    "opt2": "గొర్రెల మంద వలె",
    "opt3": "మంచు వలె",
    "opt4": "పాలు వలె",
    "correct": "గొర్రెల మంద వలె",
    "explanation": "పరమగీతము 4:2 - నీ పళ్లు కత్తెర వేయబడబోవునప్పుడు కడగబడి పైకి వచ్చిన గొర్రెల మంద వలె ఉన్నవి.",
    "book": "SongofSolomon",
    "category": "OldTestament",
    "chapter": 4
  },
  {
    "question": "ఆమె పెదవులు దేనిని పోలియున్నవి?",
    "opt1": "ఎర్రని దారమును",
    "opt2": "గులాబీ రేకును",
    "opt3": "పండును",
    "opt4": "తేనెను",
    "correct": "ఎర్రని దారమును",
    "explanation": "పరమగీతము 4:3 - నీ పెదవులు ఎర్రని దారమును పోలియున్నవి.",
    "book": "SongofSolomon",
    "category": "OldTestament",
    "chapter": 4
  },
  {
    "question": "ఆమె బుగ్గలు (Temples) దేని వలె ఉన్నవి?",
    "opt1": "ఆపిల్ పండు వలె",
    "opt2": "దానిమ్మ బద్ద వలె",
    "opt3": "పువ్వు వలె",
    "opt4": "చంద్రుని వలె",
    "correct": "దానిమ్మ బద్ద వలె",
    "explanation": "పరమగీతము 4:3 - నీ ముసుగుగుండా నీ బుగ్గలు దానిమ్మ బద్ద వలె ఉన్నవి.",
    "book": "SongofSolomon",
    "category": "OldTestament",
    "chapter": 4
  },
  {
    "question": "ఆమె మెడ దేనిని పోలియున్నది?",
    "opt1": "ఏనుగు దంతమును",
    "opt2": "దావీదు గోపురమును (Tower of David)",
    "opt3": "స్తంభమును",
    "opt4": "వృక్షమును",
    "correct": "దావీదు గోపురమును (Tower of David)",
    "explanation": "పరమగీతము 4:4 - ఆయుధములను ఉంచుటకై కట్టిన దావీదు గోపురమును నీ మెడ పోలియున్నది.",
    "book": "SongofSolomon",
    "category": "OldTestament",
    "chapter": 4
  },
  {
    "question": "ఎండ చల్లారి నీడలు పారిపోవు వరకు ప్రియుడు ఎక్కడికి వెళ్లెదను అనెను?",
    "opt1": "ఇంటికి",
    "opt2": "తోటలోనికి",
    "opt3": "రక్త బోళము గల పర్వతమునకును సాంబ్రాణి గల మెట్టకును",
    "opt4": "యెరూషలేమునకు",
    "correct": "రక్త బోళము గల పర్వతమునకును సాంబ్రాణి గల మెట్టకును",
    "explanation": "పరమగీతము 4:6 - ఎండ చల్లారి నీడలు పారిపోవు వరకు నేను రక్త బోళము గల పర్వతమునకును సాంబ్రాణి గల మెట్టకును వెళ్లెదను.",
    "book": "SongofSolomon",
    "category": "OldTestament",
    "chapter": 4
  },
  {
    "question": "ప్రియుడు ఆమెతో ఎక్కడి నుండి రమ్మని పిలిచెను?",
    "opt1": "యెరూషలేము నుండి",
    "opt2": "లెబానోను నుండి",
    "opt3": "షారోను నుండి",
    "opt4": "ఐగుప్తు నుండి",
    "correct": "లెబానోను నుండి",
    "explanation": "పరమగీతము 4:8 - నా పెండ్లి కుమార్తె, లెబానోను నుండి నాతో రమ్ము.",
    "book": "SongofSolomon",
    "category": "OldTestament",
    "chapter": 4
  },
  {
    "question": "ఆమె దేనితో అతని హృదయమును ఆకర్షించెను?",
    "opt1": "మాటలతో",
    "opt2": "పాటతో",
    "opt3": "ఒక చూపుతోను, మెడలోని ఒక గొలుసుతోను",
    "opt4": "బహుమానముతో",
    "correct": "ఒక చూపుతోను, మెడలోని ఒక గొలుసుతోను",
    "explanation": "పరమగీతము 4:9 - నీవొక చూపుతో నా హృదయమును ఆకర్షించితివి, నీ మెడలోని ఒక గొలుసుతో నా హృదయమును ఆకర్షించితివి.",
    "book": "SongofSolomon",
    "category": "OldTestament",
    "chapter": 4
  },
  {
    "question": "ఆమె పెదవుల నుండి ఏమి కారుచున్నది?",
    "opt1": "పాలు",
    "opt2": "తేనె",
    "opt3": "ద్రాక్షారసము",
    "opt4": "నీళ్ళు",
    "correct": "తేనె",
    "explanation": "పరమగీతము 4:11 - నా పెండ్లి కుమార్తె, నీ పెదవుల నుండి తేనె కారుచున్నది.",
    "book": "SongofSolomon",
    "category": "OldTestament",
    "chapter": 4
  },
  {
    "question": "నా సహోదరి, నా పెండ్లి కుమార్తె ఎటువంటిది?",
    "opt1": "ఒక నది",
    "opt2": "మూయబడిన ఉద్యానవనము, కట్టబడిన జలకూపము, ముద్రింపబడిన ఊట",
    "opt3": "బహిరంగ స్థలము",
    "opt4": "అడవి",
    "correct": "మూయబడిన ఉద్యానవనము, కట్టబడిన జలకూపము, ముద్రింపబడిన ఊట",
    "explanation": "పరమగీతము 4:12 - నా సహోదరి నా పెండ్లి కుమార్తె మూయబడిన ఉద్యానవనము, కట్టబడిన జలకూపము, ముద్రింపబడిన ఊట.",
    "book": "SongofSolomon",
    "category": "OldTestament",
    "chapter": 4
  },
  {
    "question": "ఆమె కోరిక ఏమిటి?",
    "opt1": "ఉత్తరవాయువూ, లెమ్ము; దక్షిణవాయువూ, రమ్ము; నా ఉద్యానవనము మీద విసురుము",
    "opt2": "వర్షము కురియును గాక",
    "opt3": "ఎండ కాచును గాక",
    "opt4": "శీతలముగా ఉండును గాక",
    "correct": "ఉత్తరవాయువూ, లెమ్ము; దక్షిణవాయువూ, రమ్ము; నా ఉద్యానవనము మీద విసురుము",
    "explanation": "పరమగీతము 4:16 - ఉత్తరవాయువూ, లెమ్ము; దక్షిణవాయువూ, రమ్ము; నా ఉద్యానవనము మీద విసురుము.",
    "book": "SongofSolomon",
    "category": "OldTestament",
    "chapter": 4
  }
]
  
